{
  "data": [
    {
      "stock_id": 74,
      "open": 147.42,
      "close": 146.32,
      "high": 147.62,
      "low": 146.31,
      "last": 147.13,
      "volume": 50892.0,
      "date": "2023-10-24T15:00:00+0000"
    },
    {
      "stock_id": 74,
      "open": 147.42,
      "close": 146.32,
      "high": 147.57,
      "low": 146.31,
      "last": 147.11,
      "volume": 18472.0,
      "date": "2023-10-24T14:00:00+0000"
    },
    {
      "stock_id": 74,
      "open": 147.28,
      "close": 147.81,
      "high": 148.68,
      "low": 146.01,
      "last": 146.32,
      "volume": 5398179.0,
      "date": "2023-10-24T00:00:00+0000"
    },
    {
      "stock_id": 74,
      "open": 147.15,
      "close": 147.81,
      "high": 148.68,
      "low": 146.04,
      "last": 146.765,
      "volume": 210634.0,
      "date": "2023-10-23T19:00:00+0000"
    },
    {
      "stock_id": 74,
      "open": 147.15,
      "close": 147.81,
      "high": 148.68,
      "low": 146.04,
      "last": 147.45,
      "volume": 193659.0,
      "date": "2023-10-23T18:00:00+0000"
    },
    {
      "stock_id": 74,
      "open": 147.15,
      "close": 147.81,
      "high": 148.68,
      "low": 146.04,
      "last": 148.65,
      "volume": 173498.0,
      "date": "2023-10-23T17:00:00+0000"
    },
    {
      "stock_id": 74,
      "open": 147.15,
      "close": 147.81,
      "high": 147.6,
      "low": 146.04,
      "last": 147.215,
      "volume": 149531.0,
      "date": "2023-10-23T16:00:00+0000"
    },
    {
      "stock_id": 74,
      "open": 147.15,
      "close": 147.81,
      "high": 147.49,
      "low": 146.04,
      "last": 147.21,
      "volume": 38808.0,
      "date": "2023-10-23T15:00:00+0000"
    },
    {
      "stock_id": 74,
      "open": 147.15,
      "close": 147.81,
      "high": 147.4,
      "low": 146.04,
      "last": 147.145,
      "volume": 12867.0,
      "date": "2023-10-23T14:00:00+0000"
    },
    {
      "stock_id": 74,
      "open": 151.42,
      "close": 150.94,
      "high": 151.81,
      "low": 147.61,
      "last": 147.81,
      "volume": 5391732.0,
      "date": "2023-10-21T00:00:00+0000"
    },
    {
      "stock_id": 74,
      "open": 151.49,
      "close": 150.94,
      "high": 151.84,
      "low": 148.445,
      "last": 148.65,
      "volume": 93613.0,
      "date": "2023-10-20T19:00:00+0000"
    },
    {
      "stock_id": 74,
      "open": 151.49,
      "close": 150.94,
      "high": 151.84,
      "low": 148.74,
      "last": 149.09,
      "volume": 76475.0,
      "date": "2023-10-20T18:00:00+0000"
    },
    {
      "stock_id": 74,
      "open": 151.49,
      "close": 150.94,
      "high": 151.84,
      "low": 148.74,
      "last": 149.29,
      "volume": 61782.0,
      "date": "2023-10-20T17:00:00+0000"
    },
    {
      "stock_id": 74,
      "open": 151.49,
      "close": 150.94,
      "high": 151.84,
      "low": 148.74,
      "last": 149.5,
      "volume": 46188.0,
      "date": "2023-10-20T16:00:00+0000"
    },
    {
      "stock_id": 74,
      "open": 151.49,
      "close": 150.94,
      "high": 151.84,
      "low": 149.135,
      "last": 149.37,
      "volume": 29409.0,
      "date": "2023-10-20T15:00:00+0000"
    },
    {
      "stock_id": 74,
      "open": 151.49,
      "close": 150.94,
      "high": 151.84,
      "low": 150.75,
      "last": 151.4,
      "volume": 12694.0,
      "date": "2023-10-20T14:00:00+0000"
    },
    {
      "stock_id": 74,
      "open": 152.84,
      "close": 151.82,
      "high": 153.46,
      "low": 150.47,
      "last": 150.94,
      "volume": 6041145.0,
      "date": "2023-10-20T00:00:00+0000"
    },
    {
      "stock_id": 74,
      "open": 152.91,
      "close": 151.82,
      "high": 153.395,
      "low": 150.95,
      "last": 151.135,
      "volume": 108599.0,
      "date": "2023-10-19T19:00:00+0000"
    },
    {
      "stock_id": 74,
      "open": 152.91,
      "close": 151.82,
      "high": 153.395,
      "low": 151.165,
      "last": 151.98,
      "volume": 98267.0,
      "date": "2023-10-19T18:00:00+0000"
    },
    {
      "stock_id": 74,
      "open": 152.91,
      "close": 151.82,
      "high": 153.32,
      "low": 151.165,
      "last": 153.01,
      "volume": 89411.0,
      "date": "2023-10-19T17:00:00+0000"
    },
    {
      "stock_id": 74,
      "open": 152.91,
      "close": 151.82,
      "high": 153.32,
      "low": 151.57,
      "last": 152.33,
      "volume": 75367.0,
      "date": "2023-10-19T16:00:00+0000"
    },
    {
      "stock_id": 74,
      "open": 152.91,
      "close": 151.82,
      "high": 153.32,
      "low": 151.57,
      "last": 152.085,
      "volume": 58298.0,
      "date": "2023-10-19T15:00:00+0000"
    },
    {
      "stock_id": 74,
      "open": 152.91,
      "close": 151.82,
      "high": 153.25,
      "low": 151.57,
      "last": 152.29,
      "volume": 28835.0,
      "date": "2023-10-19T14:00:00+0000"
    },
    {
      "stock_id": 74,
      "open": 152.92,
      "close": 154.26,
      "high": 154.03,
      "low": 151.45,
      "last": 151.82,
      "volume": 4837519.0,
      "date": "2023-10-19T00:00:00+0000"
    },
    {
      "stock_id": 74,
      "open": 153.03,
      "close": 154.26,
      "high": 153.97,
      "low": 152.0,
      "last": 152.49,
      "volume": 96730.0,
      "date": "2023-10-18T19:00:00+0000"
    },
    {
      "stock_id": 74,
      "open": 153.03,
      "close": 154.26,
      "high": 153.97,
      "low": 152.0,
      "last": 152.5,
      "volume": 86113.0,
      "date": "2023-10-18T18:00:00+0000"
    },
    {
      "stock_id": 74,
      "open": 153.03,
      "close": 154.26,
      "high": 153.97,
      "low": 152.18,
      "last": 152.29,
      "volume": 60371.0,
      "date": "2023-10-18T17:00:00+0000"
    },
    {
      "stock_id": 74,
      "open": 153.03,
      "close": 154.26,
      "high": 153.97,
      "low": 152.18,
      "last": 152.91,
      "volume": 52227.0,
      "date": "2023-10-18T16:00:00+0000"
    },
    {
      "stock_id": 74,
      "open": 152.86,
      "high": 152.86,
      "low": 152.86,
      "date": "2023-10-18T15:00:00+0000"
    },
    {
      "stock_id": 74,
      "open": 153.03,
      "close": 154.26,
      "high": 153.27,
      "low": 152.35,
      "last": 152.35,
      "volume": 14408.0,
      "date": "2023-10-18T14:00:00+0000"
    },
    {
      "stock_id": 74,
      "open": 152.82,
      "close": 154.3,
      "high": 154.91,
      "low": 151.89,
      "last": 154.26,
      "volume": 5098968.0,
      "date": "2023-10-18T00:00:00+0000"
    },
    {
      "stock_id": 74,
      "open": 153.02,
      "close": 154.3,
      "high": 154.895,
      "low": 151.91,
      "last": 153.73,
      "volume": 86208.0,
      "date": "2023-10-17T19:00:00+0000"
    },
    {
      "stock_id": 74,
      "open": 153.02,
      "close": 154.3,
      "high": 154.895,
      "low": 151.91,
      "last": 153.6,
      "volume": 61986.0,
      "date": "2023-10-17T18:00:00+0000"
    },
    {
      "stock_id": 74,
      "open": 153.02,
      "close": 154.3,
      "high": 154.895,
      "low": 151.91,
      "last": 153.97,
      "volume": 50289.0,
      "date": "2023-10-17T17:00:00+0000"
    },
    {
      "stock_id": 74,
      "open": 154.74,
      "high": 154.74,
      "low": 154.74,
      "date": "2023-10-17T16:00:00+0000"
    },
    {
      "stock_id": 74,
      "open": 153.02,
      "close": 154.3,
      "high": 153.86,
      "low": 151.91,
      "last": 153.7,
      "volume": 30495.0,
      "date": "2023-10-17T15:00:00+0000"
    },
    {
      "stock_id": 74,
      "open": 153.02,
      "close": 154.3,
      "high": 153.05,
      "low": 151.91,
      "last": 152.48,
      "volume": 17964.0,
      "date": "2023-10-17T14:00:00+0000"
    },
    {
      "stock_id": 74,
      "open": 153.27,
      "close": 152.75,
      "high": 154.7,
      "low": 153.105,
      "last": 153.9,
      "volume": 69621.0,
      "date": "2023-10-16T19:00:00+0000"
    },
    {
      "stock_id": 74,
      "open": 153.27,
      "close": 152.75,
      "high": 154.7,
      "low": 153.105,
      "last": 154.08,
      "volume": 52299.0,
      "date": "2023-10-16T18:00:00+0000"
    },
    {
      "stock_id": 74,
      "open": 153.27,
      "close": 152.75,
      "high": 154.7,
      "low": 153.105,
      "last": 154.08,
      "volume": 37501.0,
      "date": "2023-10-16T17:00:00+0000"
    },
    {
      "stock_id": 74,
      "open": 153.27,
      "close": 152.75,
      "high": 154.7,
      "low": 153.27,
      "last": 153.405,
      "volume": 29751.0,
      "date": "2023-10-16T16:00:00+0000"
    },
    {
      "stock_id": 74,
      "open": 153.27,
      "close": 152.75,
      "high": 154.7,
      "low": 153.27,
      "last": 154.44,
      "volume": 21704.0,
      "date": "2023-10-16T15:00:00+0000"
    },
    {
      "stock_id": 74,
      "open": 153.27,
      "close": 152.75,
      "high": 154.41,
      "low": 153.27,
      "last": 154.04,
      "volume": 6227.0,
      "date": "2023-10-16T14:00:00+0000"
    },
    {
      "stock_id": 74,
      "open": 155.245,
      "close": 155.0,
      "high": 155.37,
      "low": 152.21,
      "last": 152.52,
      "volume": 41495.0,
      "date": "2023-10-13T19:00:00+0000"
    },
    {
      "stock_id": 74,
      "open": 155.245,
      "close": 155.0,
      "high": 155.37,
      "low": 152.21,
      "last": 152.48,
      "volume": 36840.0,
      "date": "2023-10-13T18:00:00+0000"
    },
    {
      "stock_id": 74,
      "open": 155.245,
      "close": 155.0,
      "high": 155.37,
      "low": 152.735,
      "last": 153.15,
      "volume": 25443.0,
      "date": "2023-10-13T17:00:00+0000"
    },
    {
      "stock_id": 74,
      "open": 155.245,
      "close": 155.0,
      "high": 155.37,
      "low": 152.735,
      "last": 152.97,
      "volume": 20511.0,
      "date": "2023-10-13T16:00:00+0000"
    },
    {
      "stock_id": 74,
      "open": 155.245,
      "close": 155.0,
      "high": 155.37,
      "low": 153.24,
      "last": 153.38,
      "volume": 14942.0,
      "date": "2023-10-13T15:00:00+0000"
    },
    {
      "stock_id": 74,
      "open": 155.245,
      "close": 155.0,
      "high": 155.37,
      "low": 153.91,
      "last": 154.95,
      "volume": 5112.0,
      "date": "2023-10-13T14:00:00+0000"
    },
    {
      "stock_id": 74,
      "open": 158.04,
      "close": 157.33,
      "high": 158.27,
      "low": 154.23,
      "last": 155.0,
      "volume": 5643258.0,
      "date": "2023-10-13T00:00:00+0000"
    },
    {
      "stock_id": 74,
      "open": 157.775,
      "close": 157.33,
      "high": 158.06,
      "low": 154.24,
      "last": 154.98,
      "volume": 67694.0,
      "date": "2023-10-12T19:00:00+0000"
    },
    {
      "stock_id": 74,
      "open": 157.775,
      "close": 157.33,
      "high": 158.06,
      "low": 155.06,
      "last": 155.14,
      "volume": 46097.0,
      "date": "2023-10-12T18:00:00+0000"
    },
    {
      "stock_id": 74,
      "open": 157.775,
      "close": 157.33,
      "high": 158.06,
      "low": 156.37,
      "last": 157.34,
      "volume": 27662.0,
      "date": "2023-10-12T17:00:00+0000"
    },
    {
      "stock_id": 74,
      "open": 157.775,
      "close": 157.33,
      "high": 158.06,
      "low": 156.37,
      "last": 157.26,
      "volume": 19758.0,
      "date": "2023-10-12T16:00:00+0000"
    },
    {
      "stock_id": 74,
      "open": 157.775,
      "close": 157.33,
      "high": 158.06,
      "low": 156.54,
      "last": 156.6,
      "volume": 12371.0,
      "date": "2023-10-12T15:00:00+0000"
    },
    {
      "stock_id": 74,
      "open": 157.775,
      "close": 157.33,
      "high": 158.06,
      "low": 157.08,
      "last": 157.25,
      "volume": 4631.0,
      "date": "2023-10-12T14:00:00+0000"
    },
    {
      "stock_id": 74,
      "open": 156.32,
      "close": 157.66,
      "high": 158.27,
      "low": 155.74,
      "last": 157.33,
      "volume": 4452444.0,
      "date": "2023-10-12T00:00:00+0000"
    },
    {
      "stock_id": 74,
      "open": 155.63,
      "close": 157.66,
      "high": 158.23,
      "low": 155.63,
      "last": 157.005,
      "volume": 55673.0,
      "date": "2023-10-11T19:00:00+0000"
    },
    {
      "stock_id": 74,
      "open": 155.63,
      "close": 157.66,
      "high": 158.23,
      "low": 155.63,
      "last": 156.78,
      "volume": 51052.0,
      "date": "2023-10-11T18:00:00+0000"
    },
    {
      "stock_id": 74,
      "open": 155.63,
      "close": 157.66,
      "high": 158.23,
      "low": 155.63,
      "last": 156.55,
      "volume": 45265.0,
      "date": "2023-10-11T17:00:00+0000"
    },
    {
      "stock_id": 74,
      "open": 156.785,
      "high": 156.785,
      "low": 156.785,
      "date": "2023-10-11T16:00:00+0000"
    },
    {
      "stock_id": 74,
      "open": 155.63,
      "close": 157.66,
      "high": 158.23,
      "low": 155.63,
      "last": 157.47,
      "volume": 36445.0,
      "date": "2023-10-11T15:00:00+0000"
    },
    {
      "stock_id": 74,
      "open": 155.63,
      "close": 157.66,
      "high": 158.23,
      "low": 155.63,
      "last": 156.73,
      "volume": 20855.0,
      "date": "2023-10-11T14:00:00+0000"
    },
    {
      "stock_id": 74,
      "open": 156.69,
      "close": 156.72,
      "high": 159.19,
      "low": 156.295,
      "last": 157.54,
      "volume": 50854.0,
      "date": "2023-10-10T19:00:00+0000"
    },
    {
      "stock_id": 74,
      "open": 156.69,
      "close": 156.72,
      "high": 159.19,
      "low": 156.295,
      "last": 157.715,
      "volume": 30450.0,
      "date": "2023-10-10T18:00:00+0000"
    },
    {
      "stock_id": 74,
      "open": 159.19,
      "high": 159.19,
      "low": 159.19,
      "date": "2023-10-10T17:00:00+0000"
    },
    {
      "stock_id": 74,
      "open": 156.69,
      "close": 156.72,
      "high": 159.04,
      "low": 156.295,
      "last": 158.8,
      "volume": 14950.0,
      "date": "2023-10-10T16:00:00+0000"
    },
    {
      "stock_id": 74,
      "open": 156.69,
      "close": 156.72,
      "high": 158.43,
      "low": 156.295,
      "last": 158.01,
      "volume": 10154.0,
      "date": "2023-10-10T15:00:00+0000"
    },
    {
      "stock_id": 74,
      "open": 156.69,
      "close": 156.72,
      "high": 157.335,
      "low": 156.295,
      "last": 157.33,
      "volume": 3355.0,
      "date": "2023-10-10T14:00:00+0000"
    },
    {
      "stock_id": 74,
      "open": 155.83,
      "close": 157.0,
      "high": 156.84,
      "low": 154.695,
      "last": 156.72,
      "volume": 2747012.0,
      "date": "2023-10-10T00:00:00+0000"
    },
    {
      "stock_id": 74,
      "open": 155.64,
      "close": 157.0,
      "high": 156.805,
      "low": 154.895,
      "last": 156.55,
      "volume": 28553.0,
      "date": "2023-10-09T19:00:00+0000"
    },
    {
      "stock_id": 74,
      "open": 155.64,
      "close": 157.0,
      "high": 156.7,
      "low": 154.895,
      "last": 156.31,
      "volume": 25519.0,
      "date": "2023-10-09T18:00:00+0000"
    },
    {
      "stock_id": 74,
      "open": 155.64,
      "close": 157.0,
      "high": 156.27,
      "low": 154.895,
      "last": 155.41,
      "volume": 22082.0,
      "date": "2023-10-09T17:00:00+0000"
    },
    {
      "stock_id": 74,
      "open": 155.64,
      "close": 157.0,
      "high": 156.27,
      "low": 154.895,
      "last": 155.51,
      "volume": 17185.0,
      "date": "2023-10-09T16:00:00+0000"
    },
    {
      "stock_id": 74,
      "open": 155.64,
      "close": 157.0,
      "high": 156.27,
      "low": 154.895,
      "last": 155.32,
      "volume": 9654.0,
      "date": "2023-10-09T15:00:00+0000"
    },
    {
      "stock_id": 74,
      "open": 155.64,
      "close": 157.0,
      "high": 156.27,
      "low": 154.895,
      "last": 155.37,
      "volume": 4076.0,
      "date": "2023-10-09T14:00:00+0000"
    },
    {
      "stock_id": 74,
      "open": 153.4,
      "close": 155.11,
      "high": 157.92,
      "low": 153.27,
      "last": 157.78,
      "volume": 78648.0,
      "date": "2023-10-06T19:00:00+0000"
    },
    {
      "stock_id": 74,
      "open": 153.4,
      "close": 155.11,
      "high": 157.54,
      "low": 153.27,
      "last": 157.23,
      "volume": 71660.0,
      "date": "2023-10-06T18:00:00+0000"
    },
    {
      "stock_id": 74,
      "open": 153.4,
      "close": 155.11,
      "high": 157.54,
      "low": 153.27,
      "last": 156.97,
      "volume": 54458.0,
      "date": "2023-10-06T17:00:00+0000"
    },
    {
      "stock_id": 74,
      "open": 153.4,
      "close": 155.11,
      "high": 157.5,
      "low": 153.27,
      "last": 157.42,
      "volume": 44081.0,
      "date": "2023-10-06T16:00:00+0000"
    },
    {
      "stock_id": 74,
      "open": 153.4,
      "close": 155.11,
      "high": 155.83,
      "low": 153.27,
      "last": 155.33,
      "volume": 27817.0,
      "date": "2023-10-06T15:00:00+0000"
    },
    {
      "stock_id": 74,
      "open": 153.4,
      "close": 155.11,
      "high": 154.62,
      "low": 153.27,
      "last": 153.98,
      "volume": 6670.0,
      "date": "2023-10-06T14:00:00+0000"
    },
    {
      "stock_id": 74,
      "open": 158.46,
      "close": 157.97,
      "high": 159.14,
      "low": 154.8,
      "last": 155.77,
      "volume": 75937.0,
      "date": "2023-10-05T19:00:00+0000"
    },
    {
      "stock_id": 74,
      "open": 158.46,
      "close": 157.97,
      "high": 159.14,
      "low": 154.8,
      "last": 155.79,
      "volume": 61272.0,
      "date": "2023-10-05T18:00:00+0000"
    },
    {
      "stock_id": 74,
      "open": 158.46,
      "close": 157.97,
      "high": 159.14,
      "low": 154.8,
      "last": 155.59,
      "volume": 52484.0,
      "date": "2023-10-05T17:00:00+0000"
    },
    {
      "stock_id": 74,
      "open": 155.35,
      "high": 155.35,
      "low": 155.35,
      "date": "2023-10-05T16:00:00+0000"
    },
    {
      "stock_id": 74,
      "open": 158.46,
      "close": 157.97,
      "high": 159.14,
      "low": 155.06,
      "last": 155.39,
      "volume": 37353.0,
      "date": "2023-10-05T15:00:00+0000"
    },
    {
      "stock_id": 74,
      "open": 158.46,
      "close": 157.97,
      "high": 159.14,
      "low": 156.575,
      "last": 156.63,
      "volume": 23136.0,
      "date": "2023-10-05T14:00:00+0000"
    },
    {
      "stock_id": 74,
      "open": 157.66,
      "close": 157.25,
      "high": 158.48,
      "low": 156.49,
      "last": 157.97,
      "volume": 4129857.0,
      "date": "2023-10-05T00:00:00+0000"
    },
    {
      "stock_id": 74,
      "open": 157.89,
      "close": 157.25,
      "high": 158.005,
      "low": 156.49,
      "last": 157.49,
      "volume": 113881.0,
      "date": "2023-10-04T19:00:00+0000"
    },
    {
      "stock_id": 74,
      "open": 157.89,
      "close": 157.25,
      "high": 158.005,
      "low": 156.49,
      "last": 157.06,
      "volume": 83134.0,
      "date": "2023-10-04T18:00:00+0000"
    },
    {
      "stock_id": 74,
      "open": 157.89,
      "close": 157.25,
      "high": 158.005,
      "low": 156.49,
      "last": 157.46,
      "volume": 63810.0,
      "date": "2023-10-04T17:00:00+0000"
    },
    {
      "stock_id": 74,
      "open": 157.89,
      "close": 157.25,
      "high": 158.005,
      "low": 156.49,
      "last": 157.62,
      "volume": 45170.0,
      "date": "2023-10-04T16:00:00+0000"
    },
    {
      "stock_id": 74,
      "open": 157.89,
      "close": 157.25,
      "high": 157.89,
      "low": 156.49,
      "last": 156.67,
      "volume": 29188.0,
      "date": "2023-10-04T15:00:00+0000"
    },
    {
      "stock_id": 74,
      "open": 157.89,
      "close": 157.25,
      "high": 157.89,
      "low": 156.8,
      "last": 157.32,
      "volume": 11247.0,
      "date": "2023-10-04T14:00:00+0000"
    },
    {
      "stock_id": 74,
      "open": 158.11,
      "close": 159.95,
      "high": 160.4,
      "low": 156.34,
      "last": 157.25,
      "volume": 3510651.0,
      "date": "2023-10-04T00:00:00+0000"
    },
    {
      "stock_id": 74,
      "open": 158.36,
      "close": 159.95,
      "high": 160.36,
      "low": 156.72,
      "last": 156.77,
      "volume": 46888.0,
      "date": "2023-10-03T19:00:00+0000"
    },
    {
      "stock_id": 74,
      "open": 158.36,
      "close": 159.95,
      "high": 160.36,
      "low": 157.275,
      "last": 157.565,
      "volume": 35842.0,
      "date": "2023-10-03T18:00:00+0000"
    },
    {
      "stock_id": 74,
      "open": 158.36,
      "close": 159.95,
      "high": 160.36,
      "low": 157.745,
      "last": 158.78,
      "volume": 25169.0,
      "date": "2023-10-03T17:00:00+0000"
    },
    {
      "stock_id": 74,
      "open": 158.36,
      "close": 159.95,
      "high": 160.36,
      "low": 157.745,
      "last": 158.06,
      "volume": 17980.0,
      "date": "2023-10-03T16:00:00+0000"
    }
  ]
}